quintoandar_kafka/__init__.py
quintoandar_kafka/consumer.py
quintoandar_kafka/idempotence_client.py
quintoandar_kafka-2.0.0.dist-info/LICENSE
quintoandar_kafka-2.0.0.dist-info/METADATA
quintoandar_kafka-2.0.0.dist-info/WHEEL
quintoandar_kafka-2.0.0.dist-info/top_level.txt
quintoandar_kafka-2.0.0.dist-info/RECORD
