Metadata-Version: 2.1
Name: quintoandar-kafka
Version: 2.0.0
Summary: Checks messages to avoid reprocessing events.
Home-page: https://github.com/quintoandar/kafka-python
Author: QuintoAndar
Author-email: rodrigo.oliveira@quintoandar.com.br
License: UNKNOWN
Platform: UNKNOWN
Classifier: Programming Language :: Python :: 3
Classifier: License :: OSI Approved :: MIT License
Classifier: Operating System :: OS Independent
Requires-Dist: redis (==2.10.6)
Requires-Dist: retrying (==1.3.3)
Requires-Dist: kafka-python (==1.4.6)
